eleocm/__init__.py
eleocm/eleocm_oil_predict.py
eleocm/__pycache__/__init__.cpython-39.pyc
eleocm/__pycache__/eleocm_oil_predict.cpython-39.pyc
eleocm_oil-1.3.0.dist-info/LICENSE
eleocm_oil-1.3.0.dist-info/METADATA
eleocm_oil-1.3.0.dist-info/WHEEL
eleocm_oil-1.3.0.dist-info/top_level.txt
eleocm_oil-1.3.0.dist-info/RECORD
